README.md
setup.py
python_thycotic.egg-info/PKG-INFO
python_thycotic.egg-info/SOURCES.txt
python_thycotic.egg-info/dependency_links.txt
python_thycotic.egg-info/not-zip-safe
python_thycotic.egg-info/requires.txt
python_thycotic.egg-info/top_level.txt
thycotic/__init__.py
thycotic/api.py
thycotic/models.py