Metadata-Version: 2.1
Name: python-thycotic
Version: 0.1.0
Summary: Python wrapper for Thycotic Secret Server API
Home-page: https://github.com/ksalman/python_thycotic
Author: ksalman
Author-email: 1268871+ksalman@users.noreply.github.com
License: Apache Software License
Platform: UNKNOWN
